ak_pdf2md/__init__.py
ak_pdf2md/cli_app.py
ak_pdf2md/parser.py
ak_pdf2md/utils/config_parser.py
ak_pdf2md-0.0.3.dist-info/entry_points.txt
ak_pdf2md-0.0.3.dist-info/LICENSE
ak_pdf2md-0.0.3.dist-info/WHEEL
ak_pdf2md-0.0.3.dist-info/METADATA
ak_pdf2md-0.0.3.dist-info/RECORD
