Metadata-Version: 2.1
Name: ak_pdf2md
Version: 0.0.3
Summary: Convert PDF to Markdown using LlamaParse
Author-email: Arun Kishore <pypi@rpakishore.co.in>
Requires-Python: >=3.11.0
Classifier: License :: OSI Approved :: Mozilla Public License 2.0 (MPL 2.0)
Requires-Dist: typer[all]
Requires-Dist: requests
Requires-Dist: rich
Requires-Dist: llama-index
Requires-Dist: llama-parse
Requires-Dist: ipykernel ; extra == "dev"
Requires-Dist: ipywidgets ; extra == "dev"
Requires-Dist: pytest ; extra == "test"
Project-URL: Home, https://github.com/rpakishore/ak_pdf2md
Provides-Extra: dev
Provides-Extra: test
